cehrbert/__init__.py
cehrbert/cehrbert_utils.py
cehrbert/baseline_evaluation/__init__.py
cehrbert/baseline_evaluation/evaluation.py
cehrbert/baseline_evaluation/evaluation_parse_args.py
cehrbert/baseline_evaluation/transfer_learning_evaluation.py
cehrbert/baseline_evaluation/model_evaluators/__init__.py
cehrbert/baseline_evaluation/model_evaluators/frequency_model_evaluators.py
cehrbert/baseline_evaluation/model_evaluators/model_evaluators.py
cehrbert/data_generators/__init__.py
cehrbert/data_generators/hf_data_generator/__init__.py
cehrbert/data_generators/hf_data_generator/cache_util.py
cehrbert/data_generators/hf_data_generator/hf_dataset.py
cehrbert/data_generators/hf_data_generator/hf_dataset_collator.py
cehrbert/data_generators/hf_data_generator/hf_dataset_mapping.py
cehrbert/data_generators/hf_data_generator/meds_utils.py
cehrbert/data_generators/hf_data_generator/patient_block.py
cehrbert/data_generators/hf_data_generator/sample_packing_sampler.py
cehrbert/data_generators/hf_data_generator/meds_to_cehrbert_conversion_rules/__init__.py
cehrbert/data_generators/hf_data_generator/meds_to_cehrbert_conversion_rules/meds_to_cehrbert_base.py
cehrbert/data_generators/hf_data_generator/meds_to_cehrbert_conversion_rules/meds_to_cehrbert_micmic4.py
cehrbert/data_generators/hf_data_generator/meds_to_cehrbert_conversion_rules/meds_to_cehrbert_omop.py
cehrbert/linear_prob/__init__.py
cehrbert/linear_prob/compute_cehrbert_features.py
cehrbert/linear_prob/train_with_cehrbert_features.py
cehrbert/med_extension/__init__.py
cehrbert/med_extension/schema_extension.py
cehrbert/models/__init__.py
cehrbert/models/evaluation_models.py
cehrbert/models/hf_models/__init__.py
cehrbert/models/hf_models/config.py
cehrbert/models/hf_models/hf_cehrbert.py
cehrbert/models/hf_models/hf_modeling_outputs.py
cehrbert/models/hf_models/tokenization_hf_cehrbert.py
cehrbert/models/hf_models/tokenization_utils.py
cehrbert/runners/__init__.py
cehrbert/runners/data_utils.py
cehrbert-1.5.0.dist-info/licenses/LICENSE
cehrbert-1.5.0.dist-info/METADATA
cehrbert-1.5.0.dist-info/WHEEL
cehrbert-1.5.0.dist-info/entry_points.txt
cehrbert-1.5.0.dist-info/top_level.txt
cehrbert-1.5.0.dist-info/RECORD
