Metadata-Version: 2.4
Name: cehrbert
Version: 1.5.0
Summary: CEHR-BERT: Incorporating temporal information from structured EHR data to improve prediction tasks
Author-email: Chao Pang <chaopang229@gmail.com>, Xinzhuo Jiang <xj2193@cumc.columbia.edu>, Krishna Kalluri <kk3326@cumc.columbia.edu>, Nishanth Parameshwar Pavinkurve <np2689@cumc.columbia.edu>, Karthik Natarajan <kn2174@cumc.columbia.edu>
License: MIT License
Project-URL: Homepage, https://github.com/cumc-dbmi/cehr-bert
Classifier: Development Status :: 5 - Production/Stable
Classifier: Intended Audience :: Developers
Classifier: Intended Audience :: Science/Research
Classifier: License :: OSI Approved :: MIT License
Classifier: Programming Language :: Python :: 3
Requires-Python: >=3.10.0
License-File: LICENSE
Requires-Dist: dask==2024.1.1
Requires-Dist: dask[dataframe]==2024.1.1
Requires-Dist: datasets<=3.6.0,>=2.16.1
Requires-Dist: evaluate==0.4.1
Requires-Dist: fast-ml==3.68
Requires-Dist: femr<=0.2.4,>=0.2.0
Requires-Dist: Jinja2==3.1.3
Requires-Dist: meds==0.3.3
Requires-Dist: meds_reader==0.1.9
Requires-Dist: networkx>=3.2.1
Requires-Dist: numpy>=1.24.3
Requires-Dist: packaging>=23.2
Requires-Dist: pandas>=2.2.0
Requires-Dist: peft==0.10.0
Requires-Dist: Pillow>=10.3.0
Requires-Dist: pyarrow>=15.0.0
Requires-Dist: python-dateutil==2.8.2
Requires-Dist: PyYAML==6.0.1
Requires-Dist: scikit-learn==1.4.0
Requires-Dist: scipy==1.12.0
Requires-Dist: tqdm>=4.66.1
Requires-Dist: torch<=2.8.0,>=2.4.0
Requires-Dist: tokenizers>=0.19.0
Requires-Dist: transformers<=4.45.0,>=4.41.0
Requires-Dist: accelerate>=0.31.0
Requires-Dist: Werkzeug==3.0.1
Requires-Dist: wandb>=0.17.8
Requires-Dist: xgboost==2.0.3
Requires-Dist: cehrbert_data>=0.0.5
Requires-Dist: optuna>=4.0.0
Requires-Dist: polars
Provides-Extra: dev
Requires-Dist: pre-commit; extra == "dev"
Requires-Dist: pytest; extra == "dev"
Requires-Dist: pytest-cov; extra == "dev"
Requires-Dist: pytest-subtests; extra == "dev"
Requires-Dist: rootutils; extra == "dev"
Requires-Dist: hypothesis; extra == "dev"
Requires-Dist: black; extra == "dev"
Dynamic: license-file
